RowMancer/__init__.py
RowMancer/cli.py
tests/__init__.py
tests/cli_test.py
RowMancer-0.1.1.dist-info/LICENSE
RowMancer-0.1.1.dist-info/METADATA
RowMancer-0.1.1.dist-info/WHEEL
RowMancer-0.1.1.dist-info/entry_points.txt
RowMancer-0.1.1.dist-info/top_level.txt
RowMancer-0.1.1.dist-info/RECORD
