Metadata-Version: 2.1
Name: RowMancer
Version: 0.1.1
License-File: LICENSE
Requires-Dist: click
Requires-Dist: rich
